postfix_mta_sts_resolver/__init__.py
postfix_mta_sts_resolver/__main__.py
postfix_mta_sts_resolver/asdnotify.py
postfix_mta_sts_resolver/base_cache.py
postfix_mta_sts_resolver/constants.py
postfix_mta_sts_resolver/daemon.py
postfix_mta_sts_resolver/defaults.py
postfix_mta_sts_resolver/internal_cache.py
postfix_mta_sts_resolver/netstring.py
postfix_mta_sts_resolver/postgres_cache.py
postfix_mta_sts_resolver/proactive_fetcher.py
postfix_mta_sts_resolver/redis_cache.py
postfix_mta_sts_resolver/resolver.py
postfix_mta_sts_resolver/responder.py
postfix_mta_sts_resolver/sqlite_cache.py
postfix_mta_sts_resolver/utils.py
postfix_mta_sts_resolver-1.5.1.dist-info/licenses/LICENSE
postfix_mta_sts_resolver-1.5.1.dist-info/METADATA
postfix_mta_sts_resolver-1.5.1.dist-info/WHEEL
postfix_mta_sts_resolver-1.5.1.dist-info/entry_points.txt
postfix_mta_sts_resolver-1.5.1.dist-info/top_level.txt
postfix_mta_sts_resolver-1.5.1.dist-info/zip-safe
postfix_mta_sts_resolver-1.5.1.dist-info/RECORD
