Metadata-Version: 2.4
Name: postfix_mta_sts_resolver
Version: 1.5.1
Summary: Daemon which provides TLS client policy for Postfix via socketmap, according to domain MTA-STS policy
Home-page: https://github.com/Snawoot/postfix-mta-sts-resolver
Author: Vladislav Yarmak
Author-email: vladislav-ex-src@vm-0.com
License: MIT
Classifier: Programming Language :: Python :: 3.5
Classifier: License :: OSI Approved :: MIT License
Classifier: Operating System :: OS Independent
Classifier: Development Status :: 5 - Production/Stable
Classifier: Environment :: No Input/Output (Daemon)
Classifier: Intended Audience :: System Administrators
Classifier: Natural Language :: English
Classifier: Topic :: Communications :: Email :: Mail Transport Agents
Classifier: Topic :: Internet
Classifier: Topic :: Security
Requires-Python: >=3.5.3
License-File: LICENSE
Requires-Dist: aiodns>=1.1.1
Requires-Dist: aiohttp>=3.4.4
Requires-Dist: PyYAML>=3.12
Provides-Extra: sqlite
Requires-Dist: aiosqlite>=0.10.0; extra == "sqlite"
Provides-Extra: redis
Requires-Dist: redis>=4.2.0rc1; extra == "redis"
Provides-Extra: postgres
Requires-Dist: asyncpg>=0.27; extra == "postgres"
Provides-Extra: dev
Requires-Dist: pytest>=3.0.0; extra == "dev"
Requires-Dist: pytest-cov; extra == "dev"
Requires-Dist: pytest-asyncio; extra == "dev"
Requires-Dist: pytest-timeout; extra == "dev"
Requires-Dist: pylint; extra == "dev"
Requires-Dist: tox; extra == "dev"
Requires-Dist: coverage; extra == "dev"
Requires-Dist: setuptools>=38.6.0; extra == "dev"
Requires-Dist: wheel>=0.31.0; extra == "dev"
Requires-Dist: twine>=1.11.0; extra == "dev"
Requires-Dist: cryptography>=1.6; extra == "dev"
Provides-Extra: uvloop
Requires-Dist: uvloop>=0.11.0; extra == "uvloop"
Dynamic: author
Dynamic: author-email
Dynamic: classifier
Dynamic: description
Dynamic: description-content-type
Dynamic: home-page
Dynamic: license
Dynamic: license-file
Dynamic: provides-extra
Dynamic: requires-dist
Dynamic: requires-python
Dynamic: summary
